[
  {
    "start_station_name": "Serpentine Car Park, Hyde Park"
  },
  {
    "start_station_name": "Speakers' Corner 1, Hyde Park"
  },
  {
    "start_station_name": "Queen Street 2, Bank"
  },
  {
    "start_station_name": "Teviot Street, Poplar"
  },
  {
    "start_station_name": "Wandsworth Rd, Isley Court, Wandsworth Road"
  },
  {
    "start_station_name": "Gunmakers Lane, Old Ford"
  },
  {
    "start_station_name": "Wright's Lane, Kensington"
  },
  {
    "start_station_name": "Somerset House, Strand"
  },
  {
    "start_station_name": "Triangle Car Park, Hyde Park"
  },
  {
    "start_station_name": "Aquatic Centre, Queen Elizabeth Olympic Park"
  },
  {
    "start_station_name": "Farm Street, Mayfair"
  },
  {
    "start_station_name": "Wood Street, Guildhall"
  },
  {
    "start_station_name": "Southwark Station 2, Southwark"
  },
  {
    "start_station_name": "Park Lane , Hyde Park"
  },
  {
    "start_station_name": "Abbotsbury Road, Holland Park"
  },
  {
    "start_station_name": "Bromley High Street, Bow"
  },
  {
    "start_station_name": "Tower Gardens , Tower"
  },
  {
    "start_station_name": "Claverton Street, Pimlico"
  },
  {
    "start_station_name": "Waterloo Place, St. James's"
  },
  {
    "start_station_name": "Upper Richmond Road, Putney"
  },
  {
    "start_station_name": "St. John's Road, Clapham Junction"
  },
  {
    "start_station_name": "New Kent Road, Borough"
  },
  {
    "start_station_name": "Handyside Street, King's Cross"
  },
  {
    "start_station_name": "Prince Albert Road, The Regent's Park"
  },
  {
    "start_station_name": "North Audley Street, Mayfair"
  },
  {
    "start_station_name": "Frampton Street, Paddington"
  },
  {
    "start_station_name": "Green Park Station, Mayfair"
  },
  {
    "start_station_name": "London Zoo,  The Regent's Park"
  },
  {
    "start_station_name": "Queen's Gate, Kensington Gardens"
  },
  {
    "start_station_name": "Newby Place, Poplar"
  },
  {
    "start_station_name": "William IV Street, Strand"
  },
  {
    "start_station_name": "Bramham Gardens, Earl's Court"
  },
  {
    "start_station_name": "Fournier Street, Whitechapel"
  },
  {
    "start_station_name": "Park Road (Baker Street), The Regent's Park"
  },
  {
    "start_station_name": "Seville Street, Knightsbridge"
  },
  {
    "start_station_name": "Eaton Square, Belgravia"
  },
  {
    "start_station_name": "Knightsbridge, Hyde Park"
  },
  {
    "start_station_name": "Belford House, Haggerston"
  },
  {
    "start_station_name": "Leonard Circus , Shoreditch"
  },
  {
    "start_station_name": "Richmond Way, Shepherd's Bush"
  },
  {
    "start_station_name": "Vauxhall Cross, Vauxhall"
  },
  {
    "start_station_name": "Harrowby Street, Marylebone"
  },
  {
    "start_station_name": "Shoreditch High Street, Shoreditch"
  },
  {
    "start_station_name": "Austin Road, Battersea Park"
  },
  {
    "start_station_name": "Hyde Park Corner, Hyde Park"
  },
  {
    "start_station_name": "Bolsover Street, Fitzrovia"
  },
  {
    "start_station_name": "Goldsmith's Row, Haggerston"
  },
  {
    "start_station_name": "Finsbury Circus, Liverpool Street"
  },
  {
    "start_station_name": "Paddington Green Police Station, Paddington"
  },
  {
    "start_station_name": "Tyers Gate, Bermondsey"
  },
  {
    "start_station_name": "Fulham Broadway, Walham Green"
  },
  {
    "start_station_name": "Dock Street, Wapping"
  },
  {
    "start_station_name": "The Tennis Courts, The Regent's Park"
  },
  {
    "start_station_name": "Usk Road, Battersea"
  },
  {
    "start_station_name": "Tanner Street, Bermondsey"
  },
  {
    "start_station_name": "Arlington Road, Camden Town"
  },
  {
    "start_station_name": "Wendon Street, Old Ford"
  },
  {
    "start_station_name": "Embankment (Savoy), Strand"
  },
  {
    "start_station_name": "Clerkenwell Green, Clerkenwell"
  },
  {
    "start_station_name": "Westminster Bridge Road, Elephant & Castle"
  },
  {
    "start_station_name": "Eagle Wharf Road, Hoxton"
  },
  {
    "start_station_name": "Rainville Road, Hammersmith"
  },
  {
    "start_station_name": "Storey's Gate, Westminster"
  },
  {
    "start_station_name": "Bishop's Bridge Road West, Bayswater"
  },
  {
    "start_station_name": "Beaumont Street, Marylebone"
  },
  {
    "start_station_name": "Flood Street, Chelsea"
  },
  {
    "start_station_name": "De Vere Gardens, Kensington"
  },
  {
    "start_station_name": "Albert Gate, Hyde Park"
  },
  {
    "start_station_name": "Roscoe Street, St. Luke's"
  },
  {
    "start_station_name": "Speakers' Corner 2, Hyde Park"
  },
  {
    "start_station_name": "Black Lion Gate, Kensington Gardens"
  },
  {
    "start_station_name": "Cadogan Gardens, Chelsea"
  },
  {
    "start_station_name": "Whiteley's, Bayswater"
  },
  {
    "start_station_name": "Cartwright Gardens , Bloomsbury"
  },
  {
    "start_station_name": "Warwick Avenue Station, Maida Vale"
  },
  {
    "start_station_name": "Stonecutter Street, Holborn"
  },
  {
    "start_station_name": "New Globe Walk, Bankside"
  },
  {
    "start_station_name": "Parsons Green Station, Parsons Green"
  },
  {
    "start_station_name": "Aldersgate Street, Barbican"
  },
  {
    "start_station_name": "Crisp Road, Hammersmith"
  },
  {
    "start_station_name": "Walworth Road, Elephant & Castle"
  },
  {
    "start_station_name": "Buckingham Gate, Westminster"
  },
  {
    "start_station_name": "Vincent Street, Pimlico"
  },
  {
    "start_station_name": "Golden Square, Soho"
  },
  {
    "start_station_name": "Brushfield Street, Liverpool Street"
  },
  {
    "start_station_name": "Whitehall Place, Strand"
  },
  {
    "start_station_name": "Plough Terrace, Clapham Junction"
  },
  {
    "start_station_name": "South Kensington Station, South Kensington"
  },
  {
    "start_station_name": "Chelsea Green, Chelsea"
  },
  {
    "start_station_name": "Dunston Road , Haggerston"
  },
  {
    "start_station_name": "Kennington Road Post Office, Oval"
  },
  {
    "start_station_name": "Moorfields, Moorgate"
  },
  {
    "start_station_name": "Lord's, St. John's Wood"
  },
  {
    "start_station_name": "Disraeli Road, Putney"
  },
  {
    "start_station_name": "All Saints Church, Portobello"
  },
  {
    "start_station_name": "Bonny Street, Camden Town"
  },
  {
    "start_station_name": "Tate Modern, Bankside"
  },
  {
    "start_station_name": "Marylebone Lane, Marylebone"
  },
  {
    "start_station_name": "Craven Street, Strand"
  },
  {
    "start_station_name": "Langdon Park, Poplar"
  },
  {
    "start_station_name": "All Saints' Road, Portobello"
  },
  {
    "start_station_name": "Westbourne Park Road, Portobello"
  },
  {
    "start_station_name": "Pritchard's Road, Bethnal Green"
  },
  {
    "start_station_name": "Palace Gate, Kensington Gardens"
  },
  {
    "start_station_name": "Braham Street, Aldgate"
  },
  {
    "start_station_name": "Queen Mother Sports Centre, Victoria"
  },
  {
    "start_station_name": "Harcourt Terrace, West Brompton"
  },
  {
    "start_station_name": "Lancaster Gate , Bayswater"
  },
  {
    "start_station_name": "Bankside Mix, Bankside"
  },
  {
    "start_station_name": "Hoxton Street, Hoxton"
  },
  {
    "start_station_name": "Belgrave Square, Belgravia"
  },
  {
    "start_station_name": "Thornfield House, Poplar"
  },
  {
    "start_station_name": "Gloucester Road (Central), South Kensington"
  },
  {
    "start_station_name": "Penywern Road, Earl's Court"
  },
  {
    "start_station_name": "Knaresborough Place, Earl's Court"
  },
  {
    "start_station_name": "New Kent Road, The Borough"
  },
  {
    "start_station_name": "Paddington Street, Marylebone"
  },
  {
    "start_station_name": "Ravenscourt Park Station, Hammersmith"
  },
  {
    "start_station_name": "Cloudesley Road, Angel"
  },
  {
    "start_station_name": "Hereford Road, Bayswater"
  },
  {
    "start_station_name": "Pitfield Street North,Hoxton"
  },
  {
    "start_station_name": "West Smithfield Rotunda, Farringdon"
  },
  {
    "start_station_name": "Wellington Arch, Hyde Park"
  },
  {
    "start_station_name": "Duke Street Hill, London Bridge"
  },
  {
    "start_station_name": "Brick Lane Market, Shoreditch"
  },
  {
    "start_station_name": "Manfred Road, East Putney"
  },
  {
    "start_station_name": "Putney Pier, Wandsworth"
  },
  {
    "start_station_name": "Maclise Road, Olympia"
  },
  {
    "start_station_name": "Victoria Park Road, Hackney Central"
  },
  {
    "start_station_name": "Graham Street, Angel"
  },
  {
    "start_station_name": "Ingrave Street, Clapham Junction"
  },
  {
    "start_station_name": "Berry Street, Clerkenwell"
  },
  {
    "start_station_name": "Waterloo Station 2, Waterloo"
  },
  {
    "start_station_name": "Belgrave Road, Victoria"
  },
  {
    "start_station_name": "Whiston Road, Haggerston"
  },
  {
    "start_station_name": "Little Argyll Street, West End"
  },
  {
    "start_station_name": "Exhibition Road Museums, Knightsbridge"
  },
  {
    "start_station_name": "Castlehaven Road, Camden Town"
  },
  {
    "start_station_name": "Tavistock Street, Covent Garden"
  },
  {
    "start_station_name": "Curlew Street, Shad Thames"
  },
  {
    "start_station_name": "Grosvenor Crescent, Belgravia"
  },
  {
    "start_station_name": "Tachbrook Street, Victoria"
  },
  {
    "start_station_name": "Newgate Street , St. Paul's"
  },
  {
    "start_station_name": "Fulham Park Road, Fulham"
  },
  {
    "start_station_name": "Clifton Road, Maida Vale"
  },
  {
    "start_station_name": "Old Montague Street, Whitechapel"
  },
  {
    "start_station_name": "Bourne Street, Belgravia"
  },
  {
    "start_station_name": "East Road, Hoxton"
  },
  {
    "start_station_name": "Heron Quays DLR, Canary Wharf"
  },
  {
    "start_station_name": "Clinton Road, Mile End"
  },
  {
    "start_station_name": "Harrington Square 2, Camden Town"
  },
  {
    "start_station_name": "Phillimore Gardens, Kensington"
  },
  {
    "start_station_name": "Appold Street, Liverpool Street"
  },
  {
    "start_station_name": "Sutton Street, Shadwell"
  },
  {
    "start_station_name": "Ontario Street, Elephant & Castle"
  },
  {
    "start_station_name": "Ethelburga Estate, Battersea Park"
  },
  {
    "start_station_name": "Manresa Road, Chelsea"
  },
  {
    "start_station_name": "Waterloo Road, South Bank"
  },
  {
    "start_station_name": "Carnegie Street, King's Cross"
  },
  {
    "start_station_name": "Godliman Street, St. Paul's"
  },
  {
    "start_station_name": "Cadogan Close, Victoria Park"
  },
  {
    "start_station_name": "Lower Thames Street, Monument"
  },
  {
    "start_station_name": "Jewry Street, Aldgate"
  },
  {
    "start_station_name": "Lots Road, West Chelsea"
  },
  {
    "start_station_name": "Nesham Street, Wapping"
  },
  {
    "start_station_name": "Panton Street, West End"
  },
  {
    "start_station_name": "Greenland Road, Camden Town"
  },
  {
    "start_station_name": "Concert Hall Approach 2, South Bank"
  },
  {
    "start_station_name": "Shouldham Street, Marylebone"
  },
  {
    "start_station_name": "Jubilee Gardens, South Bank"
  },
  {
    "start_station_name": "St. George's Square, Pimlico"
  },
  {
    "start_station_name": "Hortensia Road, West Brompton"
  },
  {
    "start_station_name": "Flamborough Street, Limehouse"
  },
  {
    "start_station_name": "Pembridge Villas, Notting Hill"
  },
  {
    "start_station_name": "Old Street Station, St. Luke's"
  },
  {
    "start_station_name": "Euston Road, Euston"
  },
  {
    "start_station_name": "Earnshaw Street , Covent Garden"
  },
  {
    "start_station_name": "St. George Street, Mayfair"
  },
  {
    "start_station_name": "Cheshire Street, Bethnal Green"
  },
  {
    "start_station_name": "Christopher Street, Liverpool Street"
  },
  {
    "start_station_name": "Charing Cross Hospital, Hammersmith"
  },
  {
    "start_station_name": "Mostyn Grove, Bow"
  },
  {
    "start_station_name": "Finlay Street, Fulham"
  },
  {
    "start_station_name": "Oxford Road, Putney"
  },
  {
    "start_station_name": "Warren Street Station, Euston"
  },
  {
    "start_station_name": "Sumner Place, South Kensington"
  },
  {
    "start_station_name": "Edgware Road Station, Marylebone"
  },
  {
    "start_station_name": "Islington Green, Angel"
  },
  {
    "start_station_name": "Tooley Street, Bermondsey"
  },
  {
    "start_station_name": "Ossulston Street, Somers Town"
  },
  {
    "start_station_name": "Houndsditch, Aldgate"
  },
  {
    "start_station_name": "Bury Place, Holborn"
  },
  {
    "start_station_name": "Trebovir Road, Earl's Court"
  },
  {
    "start_station_name": "St. James's Square, St. James's"
  },
  {
    "start_station_name": "Bancroft Road, Bethnal Green"
  },
  {
    "start_station_name": "Gloucester Road Station, South Kensington"
  },
  {
    "start_station_name": "Aberfeldy Street, Poplar"
  },
  {
    "start_station_name": "King Edward Street, St Pauls"
  },
  {
    "start_station_name": "Borough Road, Elephant & Castle"
  },
  {
    "start_station_name": "Commercial Street, Shoreditch"
  },
  {
    "start_station_name": "Broomhouse Lane, Parsons Green"
  },
  {
    "start_station_name": "Poured Lines, Bankside"
  },
  {
    "start_station_name": "Soho Square , Soho"
  },
  {
    "start_station_name": "British Museum, Bloomsbury"
  },
  {
    "start_station_name": "Wardour Street, Soho"
  },
  {
    "start_station_name": "Liverpool Road (N1 Centre), Angel"
  },
  {
    "start_station_name": "Alfreda Street, Battersea Park"
  },
  {
    "start_station_name": "St. Katharine's Way, Tower"
  },
  {
    "start_station_name": "Alderney Street, Pimlico"
  },
  {
    "start_station_name": "Cheapside, Bank"
  },
  {
    "start_station_name": "Fire Brigade Pier, Vauxhall"
  },
  {
    "start_station_name": "Newton Street, Covent Garden"
  },
  {
    "start_station_name": "Columbia Road, Shoreditch"
  },
  {
    "start_station_name": "The Green Bridge, Mile End"
  },
  {
    "start_station_name": "Hertford Road, De Beauvoir Town"
  },
  {
    "start_station_name": "Saunders Ness Road, Cubitt Town"
  },
  {
    "start_station_name": "Queensbridge Road, Haggerston"
  },
  {
    "start_station_name": "Finsbury Leisure Centre, St. Luke's"
  },
  {
    "start_station_name": "Westfield Library Corner, Shepherd's Bush"
  },
  {
    "start_station_name": "Wapping High Street, Wapping"
  },
  {
    "start_station_name": "Great Marlborough Street, Soho"
  },
  {
    "start_station_name": "Archbishop's Park, Waterloo"
  },
  {
    "start_station_name": "Bayswater Road, Hyde Park"
  },
  {
    "start_station_name": "Michael Road, Walham Green"
  },
  {
    "start_station_name": "Hop Exchange, The Borough"
  },
  {
    "start_station_name": "Wren Street, Holborn"
  },
  {
    "start_station_name": "Melton Street, Euston"
  },
  {
    "start_station_name": "Sun Street, Liverpool Street"
  },
  {
    "start_station_name": "Wellington Row, Bethnal Green"
  },
  {
    "start_station_name": "Bradmead, Battersea Park"
  },
  {
    "start_station_name": "Sopwith Way, Battersea Park"
  },
  {
    "start_station_name": "Pall Mall East, West End"
  },
  {
    "start_station_name": "Eccleston Place, Victoria"
  },
  {
    "start_station_name": "Charles II Street, West End"
  },
  {
    "start_station_name": "Holland Park, Kensington"
  },
  {
    "start_station_name": "Devonshire Terrace, Bayswater"
  },
  {
    "start_station_name": "York Hall, Bethnal Green"
  },
  {
    "start_station_name": "Old Quebec Street, Marylebone"
  },
  {
    "start_station_name": "Bow Road Station, Bow"
  },
  {
    "start_station_name": "Russell Square Station, Bloomsbury"
  },
  {
    "start_station_name": "Union Street, The Borough"
  },
  {
    "start_station_name": "Albert Bridge Road, Battersea Park"
  },
  {
    "start_station_name": "Wellington Road, St. John's Wood"
  },
  {
    "start_station_name": "Eel Brook Common, Walham Green"
  },
  {
    "start_station_name": "Hansard Mews, Holland Park"
  },
  {
    "start_station_name": "Cumberland Gate, Hyde Park"
  },
  {
    "start_station_name": "Farringdon Lane, Clerkenwell"
  },
  {
    "start_station_name": "Charlotte Street, Fitzrovia"
  },
  {
    "start_station_name": "Warwick Square, Pimlico"
  },
  {
    "start_station_name": "Winsland Street, Paddington"
  },
  {
    "start_station_name": "Lightermans Road, Millwall"
  },
  {
    "start_station_name": "Old Ford Road, Bethnal Green"
  },
  {
    "start_station_name": "Holy Trinity Brompton, Knightsbridge"
  },
  {
    "start_station_name": "Salmon Lane, Limehouse"
  },
  {
    "start_station_name": "High Holborn , Covent Garden"
  },
  {
    "start_station_name": "Hampstead Road, Euston"
  },
  {
    "start_station_name": "Westbridge Road, Battersea"
  },
  {
    "start_station_name": "Lambeth North Station, Waterloo"
  },
  {
    "start_station_name": "Imperial College, Knightsbridge"
  },
  {
    "start_station_name": "Podium, Queen Elizabeth Olympic Park"
  },
  {
    "start_station_name": "Broadwick Street, Soho"
  },
  {
    "start_station_name": "Strata, Elephant & Castle"
  },
  {
    "start_station_name": "Westbourne Grove, Bayswater"
  },
  {
    "start_station_name": "Portman Square, Marylebone"
  },
  {
    "start_station_name": "Park Street, Bankside"
  },
  {
    "start_station_name": "Black Prince Road, Vauxhall"
  },
  {
    "start_station_name": "Bayley Street , Bloomsbury"
  },
  {
    "start_station_name": "Fisherman's Walk West, Canary Wharf"
  },
  {
    "start_station_name": "Haggerston Road, Haggerston"
  },
  {
    "start_station_name": "Montgomery Square, Canary Wharf"
  },
  {
    "start_station_name": "Northumberland Avenue, Strand"
  },
  {
    "start_station_name": "Parkway, Camden Town"
  },
  {
    "start_station_name": "South Lambeth Road, Vauxhall"
  },
  {
    "start_station_name": "Ashmole Estate, Oval"
  },
  {
    "start_station_name": "Page Street, Westminster"
  },
  {
    "start_station_name": "Lower Marsh, Waterloo"
  },
  {
    "start_station_name": "Southampton Street, Strand"
  },
  {
    "start_station_name": "Kennington Lane Rail Bridge, Vauxhall"
  },
  {
    "start_station_name": "Belvedere Road 2, South Bank"
  },
  {
    "start_station_name": "Bricklayers Arms, Borough"
  },
  {
    "start_station_name": "Star Road, West Kensington"
  },
  {
    "start_station_name": "Cleaver Street, Kennington"
  },
  {
    "start_station_name": "Chesilton Road, Fulham"
  },
  {
    "start_station_name": "Eaton Square (South), Belgravia"
  },
  {
    "start_station_name": "Wellington Street , Strand"
  },
  {
    "start_station_name": "Nutford Place, Marylebone"
  },
  {
    "start_station_name": "Ashley Place, Victoria"
  },
  {
    "start_station_name": "Queen's Circus, Battersea Park"
  },
  {
    "start_station_name": "Hammersmith Town Hall, Hammersmith"
  },
  {
    "start_station_name": "Westfield Southern Terrace ,Shepherd's Bush"
  },
  {
    "start_station_name": "Smugglers Way, Wandsworth"
  },
  {
    "start_station_name": "Albert Embankment, Vauxhall"
  },
  {
    "start_station_name": "Wenlock Road , Hoxton"
  },
  {
    "start_station_name": "Coram Street, Bloomsbury"
  },
  {
    "start_station_name": "Clapham Common North Side, Clapham Common"
  },
  {
    "start_station_name": "Mile End Stadium, Mile End"
  },
  {
    "start_station_name": "Exhibition Road Museums, South Kensington"
  },
  {
    "start_station_name": "Queen Street 1, Bank"
  },
  {
    "start_station_name": "Limerston Street, West Chelsea"
  },
  {
    "start_station_name": "Woodstock Grove, Shepherd's Bush"
  },
  {
    "start_station_name": "Leman Street, Aldgate"
  },
  {
    "start_station_name": "Stanley Grove, Battersea"
  },
  {
    "start_station_name": "Abyssinia Close, Clapham Junction"
  },
  {
    "start_station_name": "Westfield Ariel Way, White City"
  },
  {
    "start_station_name": "Albert Gardens, Stepney"
  },
  {
    "start_station_name": "Rodney Street, Angel"
  },
  {
    "start_station_name": "Northfields, Wandsworth"
  },
  {
    "start_station_name": "Wormwood Street, Liverpool Street"
  },
  {
    "start_station_name": "Alma Road, Wandsworth"
  },
  {
    "start_station_name": "Clarendon Road, Avondale"
  },
  {
    "start_station_name": "Southern Grove, Bow"
  },
  {
    "start_station_name": "Crosswall, Tower"
  },
  {
    "start_station_name": "Westminster University, Marylebone"
  },
  {
    "start_station_name": "Bell Lane, Liverpool Street"
  },
  {
    "start_station_name": "Bridge Avenue, Hammersmith"
  },
  {
    "start_station_name": "LSBU (Borough Road), Elephant & Castle"
  },
  {
    "start_station_name": "Chepstow Villas, Notting Hill"
  },
  {
    "start_station_name": "Longford Street, Regent's Park"
  },
  {
    "start_station_name": "Timber Lodge, Queen Elizabeth Olympic Park"
  },
  {
    "start_station_name": "Lexham Gardens, Kensington"
  },
  {
    "start_station_name": "Lancaster Drive, Blackwall"
  },
  {
    "start_station_name": "Southwark Street, Bankside"
  },
  {
    "start_station_name": "Houghton Street, Strand"
  },
  {
    "start_station_name": "Endsleigh Gardens, Euston"
  },
  {
    "start_station_name": "Porchester Place, Paddington"
  },
  {
    "start_station_name": "Waterloo Bridge, South Bank"
  },
  {
    "start_station_name": "East Village, Queen Elizabeth Olympic Park"
  },
  {
    "start_station_name": "East India DLR, Blackwall"
  },
  {
    "start_station_name": "Westferry Circus, Canary Wharf"
  },
  {
    "start_station_name": "Shoreditch Court, Haggerston"
  },
  {
    "start_station_name": "Royal Avenue 1, Chelsea"
  },
  {
    "start_station_name": "Greyhound Road, Hammersmith"
  },
  {
    "start_station_name": "Battersea Park Road, Nine Elms"
  },
  {
    "start_station_name": "Millbank Tower, Pimlico"
  },
  {
    "start_station_name": "Grosvenor Square, Mayfair"
  },
  {
    "start_station_name": "Jubilee Crescent, Cubitt Town"
  },
  {
    "start_station_name": "Park Lane, Mayfair"
  },
  {
    "start_station_name": "Pott Street, Bethnal Green"
  },
  {
    "start_station_name": "Cromer Street, Bloomsbury"
  },
  {
    "start_station_name": "Surrey Lane, Battersea"
  },
  {
    "start_station_name": "Sloane Avenue, Knightsbridge"
  },
  {
    "start_station_name": "Vicarage Crescent, Battersea"
  },
  {
    "start_station_name": "Concert Hall Approach 1, South Bank"
  },
  {
    "start_station_name": "Granby Street, Shoreditch"
  },
  {
    "start_station_name": "St. Mary & St. Michael Church, Stepney"
  },
  {
    "start_station_name": "Bouverie Street, Temple"
  },
  {
    "start_station_name": "Shadwell Station, Shadwell"
  },
  {
    "start_station_name": "Exhibition Road, Knightsbridge"
  },
  {
    "start_station_name": "Abingdon Green, Westminster"
  },
  {
    "start_station_name": "Kennington Oval, Oval"
  },
  {
    "start_station_name": "Montpelier Street, Knightsbridge"
  },
  {
    "start_station_name": "Baker Street, Marylebone"
  },
  {
    "start_station_name": "Crinan Street, King's Cross"
  },
  {
    "start_station_name": "Monument Street, Monument"
  },
  {
    "start_station_name": "Howick Place, Westminster"
  },
  {
    "start_station_name": "Kingsway Southbound, Strand"
  },
  {
    "start_station_name": "Cleveland Way, Stepney"
  },
  {
    "start_station_name": "Spindrift Avenue, Millwall"
  },
  {
    "start_station_name": "Aberdeen Place, St. John's Wood"
  },
  {
    "start_station_name": "Victoria & Albert Museum, South Kensington"
  },
  {
    "start_station_name": "Usk Road, Clapham Junction"
  },
  {
    "start_station_name": "South Parade, Chelsea"
  },
  {
    "start_station_name": "Watney Market, Stepney"
  },
  {
    "start_station_name": "Bedford Way, Bloomsbury"
  },
  {
    "start_station_name": "Red Lion Street, Holborn"
  },
  {
    "start_station_name": "Snowsfields, London Bridge"
  },
  {
    "start_station_name": "Rochester Row, Westminster"
  },
  {
    "start_station_name": "South Wharf Road, Paddington"
  },
  {
    "start_station_name": "Lavington Street, Bankside"
  },
  {
    "start_station_name": "St. Luke's Church, Chelsea"
  },
  {
    "start_station_name": "Belvedere Road, South Bank"
  },
  {
    "start_station_name": "Brook Green South, Brook Green"
  },
  {
    "start_station_name": "Great Suffolk Street, The Borough"
  },
  {
    "start_station_name": "Driffield Road, Old Ford"
  },
  {
    "start_station_name": "Good's Way, King's Cross"
  },
  {
    "start_station_name": "Southwick Street, Paddington"
  },
  {
    "start_station_name": "Fore Street, Guildhall"
  },
  {
    "start_station_name": "Foley Street, Fitzrovia"
  },
  {
    "start_station_name": "Stanhope Gate, Mayfair"
  },
  {
    "start_station_name": "Cardinal Place, Victoria"
  },
  {
    "start_station_name": "Rampayne Street, Pimlico"
  },
  {
    "start_station_name": "Belgrove Street , King's Cross"
  },
  {
    "start_station_name": "Hatton Garden, Holborn"
  },
  {
    "start_station_name": "Brunswick Square, Bloomsbury"
  },
  {
    "start_station_name": "Red Lion Square, Holborn"
  },
  {
    "start_station_name": "St. Mark's Road, North Kensington"
  },
  {
    "start_station_name": "Charlbert Street, St. John's Wood"
  },
  {
    "start_station_name": "Horseferry Road, Westminster"
  },
  {
    "start_station_name": "East Ferry Road, Cubitt Town"
  },
  {
    "start_station_name": "Clapham Common North side, Clapham Common"
  },
  {
    "start_station_name": "Great Percy Street, Clerkenwell"
  },
  {
    "start_station_name": "Nevern Place, Earl's Court"
  },
  {
    "start_station_name": "Humbolt Road, Fulham"
  },
  {
    "start_station_name": "Regent's Row , Haggerston"
  },
  {
    "start_station_name": "Shoreditch Park, Hoxton"
  },
  {
    "start_station_name": "Reardon Street, Wapping"
  },
  {
    "start_station_name": "Emperor's Gate, South Kensington"
  },
  {
    "start_station_name": "Borough High Street, The Borough"
  },
  {
    "start_station_name": "Beryl Road, Hammersmith"
  },
  {
    "start_station_name": "Silverthorne Road, Battersea"
  },
  {
    "start_station_name": "Vauxhall Bridge , Pimlico"
  },
  {
    "start_station_name": "Northington Street , Holborn"
  },
  {
    "start_station_name": "Turquoise Island, Notting Hill"
  },
  {
    "start_station_name": "Sedding Street, Sloane Square"
  },
  {
    "start_station_name": "Bow Church Station, Bow"
  },
  {
    "start_station_name": "Risinghill Street, Angel"
  },
  {
    "start_station_name": "St. Peter's Terrace, Fulham"
  },
  {
    "start_station_name": "George Street, Marylebone"
  },
  {
    "start_station_name": "Tavistock Place, Bloomsbury"
  },
  {
    "start_station_name": "Wapping Lane, Wapping"
  },
  {
    "start_station_name": "Pitfield Street (North),Hoxton"
  },
  {
    "start_station_name": "Dorset Square, Marylebone"
  },
  {
    "start_station_name": "Kings Gate House, Westminster"
  },
  {
    "start_station_name": "Grove End Road, St. John's Wood"
  },
  {
    "start_station_name": "Ebury Bridge, Pimlico"
  },
  {
    "start_station_name": "Moor Street, Soho"
  },
  {
    "start_station_name": "Longford Street, The Regent's Park"
  },
  {
    "start_station_name": "Clapham Road, Lingham Street, Stockwell"
  },
  {
    "start_station_name": "Rifle Place, Avondale"
  },
  {
    "start_station_name": "Falcon Road, Clapham Junction"
  },
  {
    "start_station_name": "Queen Victoria Street, St. Paul's"
  },
  {
    "start_station_name": "Milroy Walk, South Bank"
  },
  {
    "start_station_name": "Hartington Road, Stockwell"
  },
  {
    "start_station_name": "Carey Street, Holborn"
  },
  {
    "start_station_name": "Ilchester Gardens, Bayswater"
  },
  {
    "start_station_name": "Upper Bank Street, Canary Wharf"
  },
  {
    "start_station_name": "Empire Square, The Borough"
  },
  {
    "start_station_name": "Bethnal Green Road, Shoreditch"
  },
  {
    "start_station_name": "Woodstock Street, Mayfair"
  },
  {
    "start_station_name": "Derry Street, Kensington"
  },
  {
    "start_station_name": "Pancras Road, King's Cross"
  },
  {
    "start_station_name": "Sadlers Sports Centre, Finsbury"
  },
  {
    "start_station_name": "Queen's Gate (North), Kensington"
  },
  {
    "start_station_name": "Blenheim Crescent, Ladbroke Grove"
  },
  {
    "start_station_name": "Drury Lane, Covent Garden"
  },
  {
    "start_station_name": "Monier Road, Hackney Wick"
  },
  {
    "start_station_name": "Embankment (Horse Guards), Westminster"
  },
  {
    "start_station_name": "Ashley Crescent, Battersea"
  },
  {
    "start_station_name": "Notting Hill Gate Station, Notting Hill"
  },
  {
    "start_station_name": "Manbre Road, Hammersmith"
  },
  {
    "start_station_name": "Mudchute DLR, Cubitt Town"
  },
  {
    "start_station_name": "Prince Consort Road, Knightsbridge"
  },
  {
    "start_station_name": "Kennington Road  , Vauxhall"
  },
  {
    "start_station_name": "Hampton Street, Walworth"
  },
  {
    "start_station_name": "Ackroyd Drive, Bow"
  },
  {
    "start_station_name": "Waterloo Station 1, Waterloo"
  },
  {
    "start_station_name": "Frith Street, Soho"
  },
  {
    "start_station_name": "St. Chad's Street, King's Cross"
  },
  {
    "start_station_name": "Green Park Station, West End"
  },
  {
    "start_station_name": "Great Tower Street, Monument"
  },
  {
    "start_station_name": "Princes Square, Bayswater"
  },
  {
    "start_station_name": "Hinde Street, Marylebone"
  },
  {
    "start_station_name": "Olympia Way, Olympia"
  },
  {
    "start_station_name": "City Road, Angel"
  },
  {
    "start_station_name": "Harper Road, The Borough"
  },
  {
    "start_station_name": "Stebondale Street, Cubitt Town"
  },
  {
    "start_station_name": "Torrens Street, Angel"
  },
  {
    "start_station_name": "Morie Street, Wandsworth"
  },
  {
    "start_station_name": "London Zoo Car Park, The Regent's Park"
  },
  {
    "start_station_name": "Cotton Garden Estate, Kennington"
  },
  {
    "start_station_name": "Ansell House, Stepney"
  },
  {
    "start_station_name": "Great Russell Street, Bloomsbury"
  },
  {
    "start_station_name": "Collingham Gardens, Earl's Court"
  },
  {
    "start_station_name": "St. John's Wood Church, Regent's Park"
  },
  {
    "start_station_name": "Guilford Street , Bloomsbury"
  },
  {
    "start_station_name": "Mexfield Road, East Putney"
  },
  {
    "start_station_name": "Putney Bridge Station, Fulham"
  },
  {
    "start_station_name": "Irene Road, Parsons Green"
  },
  {
    "start_station_name": "Ada Street, Hackney Central"
  },
  {
    "start_station_name": "Abingdon Villas, Kensington"
  },
  {
    "start_station_name": "Elysium Place, Fulham"
  },
  {
    "start_station_name": "Queen's Gate (Central), South Kensington"
  },
  {
    "start_station_name": "Hibbert Street, Battersea"
  },
  {
    "start_station_name": "Vereker Road, West Kensington"
  },
  {
    "start_station_name": "Wandsworth Town Station, Wandsworth"
  },
  {
    "start_station_name": "Blythe Road West, Shepherd's Bush"
  },
  {
    "start_station_name": "Vereker Road North, West Kensington"
  },
  {
    "start_station_name": "Stamford Street, South Bank"
  },
  {
    "start_station_name": "New Cavendish Street, Marylebone"
  },
  {
    "start_station_name": "Osiers Road, Wandsworth"
  },
  {
    "start_station_name": "Strand, Strand"
  },
  {
    "start_station_name": "The Vale, West Chelsea"
  },
  {
    "start_station_name": "New Fetter Lane, Holborn"
  },
  {
    "start_station_name": "Calshot Street , King's Cross"
  },
  {
    "start_station_name": "Tallis Street, Temple"
  },
  {
    "start_station_name": "Santos Road, Wandsworth"
  },
  {
    "start_station_name": "New North Road 1, Hoxton"
  },
  {
    "start_station_name": "Hewison Street, Old Ford"
  },
  {
    "start_station_name": "Jubilee Plaza, Canary Wharf"
  },
  {
    "start_station_name": "Hollybush Gardens, Bethnal Green"
  },
  {
    "start_station_name": "Northdown Street, King's Cross"
  },
  {
    "start_station_name": "Binfield Road, Stockwell"
  },
  {
    "start_station_name": "The Guildhall, Guildhall"
  },
  {
    "start_station_name": "World's End Place, West Chelsea"
  },
  {
    "start_station_name": "Rathbone Street, Fitzrovia"
  },
  {
    "start_station_name": "Norton Folgate, Liverpool Street"
  },
  {
    "start_station_name": "Burdett Road, Mile End"
  },
  {
    "start_station_name": "Teversham Lane, Stockwell"
  },
  {
    "start_station_name": "New Inn Yard, Shoreditch"
  },
  {
    "start_station_name": "Gloucester Avenue, Camden Town"
  },
  {
    "start_station_name": "Danvers Street, West Chelsea"
  },
  {
    "start_station_name": "Sackville Street, Mayfair"
  },
  {
    "start_station_name": "Finnis Street, Bethnal Green"
  },
  {
    "start_station_name": "Albany Street, The Regent's Park"
  },
  {
    "start_station_name": "Abbey Orchard Street, Westminster"
  },
  {
    "start_station_name": "Grafton Street, Mayfair"
  },
  {
    "start_station_name": "Fashion Street, Whitechapel"
  },
  {
    "start_station_name": "Neville Gill Close, Wandsworth"
  },
  {
    "start_station_name": "Sardinia Street, Holborn"
  },
  {
    "start_station_name": "Shepherd's Bush Road North, Shepherd's Bush"
  },
  {
    "start_station_name": "Fanshaw Street, Hoxton"
  },
  {
    "start_station_name": "Watney Street, Shadwell"
  },
  {
    "start_station_name": "Twig Folly Bridge, Mile End"
  },
  {
    "start_station_name": "Queen Mary's, Mile End"
  },
  {
    "start_station_name": "Ford Road, Old Ford"
  },
  {
    "start_station_name": "Philpot Street, Whitechapel"
  },
  {
    "start_station_name": "Ranelagh Gardens, Fulham"
  },
  {
    "start_station_name": "Millennium Hotel, Mayfair"
  },
  {
    "start_station_name": "Princedale Road , Holland Park"
  },
  {
    "start_station_name": "Stephendale Road, Sands End"
  },
  {
    "start_station_name": "Argyll Road, Kensington"
  },
  {
    "start_station_name": "Kennington Cross, Kennington"
  },
  {
    "start_station_name": "Felsham Road, Putney"
  },
  {
    "start_station_name": "Seymour Place, Marylebone"
  },
  {
    "start_station_name": "Rodney Road , Walworth"
  },
  {
    "start_station_name": "Swan Street, The Borough"
  },
  {
    "start_station_name": "Bethnal Green Garden, Bethnal Green"
  },
  {
    "start_station_name": "Caldwell Street, Stockwell"
  },
  {
    "start_station_name": "Aintree Street, Fulham"
  },
  {
    "start_station_name": "Napier Avenue, Millwall"
  },
  {
    "start_station_name": "Simpson Street, Clapham Junction"
  },
  {
    "start_station_name": "Hampstead Road (Cartmel), Euston"
  },
  {
    "start_station_name": "River Street , Clerkenwell"
  },
  {
    "start_station_name": "Barons Court Station, West Kensington"
  },
  {
    "start_station_name": "Imperial Wharf Station, Sands End"
  },
  {
    "start_station_name": "Harford Street, Mile End"
  },
  {
    "start_station_name": "Holborn Circus, Holborn"
  },
  {
    "start_station_name": "Gloucester Terrace, Bayswater"
  },
  {
    "start_station_name": "St. Mary Axe, Aldgate"
  },
  {
    "start_station_name": "Green Street, Mayfair"
  },
  {
    "start_station_name": "Sugden Road, Clapham"
  },
  {
    "start_station_name": "Edgware Road Station, Paddington"
  },
  {
    "start_station_name": "Vauxhall Street, Vauxhall"
  },
  {
    "start_station_name": "Millharbour, Millwall"
  },
  {
    "start_station_name": "Bruton Street, Mayfair"
  },
  {
    "start_station_name": "Walnut Tree Walk, Vauxhall"
  },
  {
    "start_station_name": "St. John's Wood Church, The Regent's Park"
  },
  {
    "start_station_name": "Cephas Street, Bethnal Green"
  },
  {
    "start_station_name": "Simpson Street, Battersea"
  },
  {
    "start_station_name": "Gloucester Road (North), Kensington"
  },
  {
    "start_station_name": "Cadogan Place, Knightsbridge"
  },
  {
    "start_station_name": "Lee Valley VeloPark, Queen Elizabeth Olympic Park"
  },
  {
    "start_station_name": "Howland Street, Fitzrovia"
  },
  {
    "start_station_name": "Royal London Hospital, Whitechapel"
  },
  {
    "start_station_name": "Addison Road, Holland Park"
  },
  {
    "start_station_name": "Finsbury Square , Moorgate"
  },
  {
    "start_station_name": "Little Brook Green, Brook Green"
  },
  {
    "start_station_name": "Elizabeth Bridge, Victoria"
  },
  {
    "start_station_name": "Phene Street, Chelsea"
  },
  {
    "start_station_name": "Gower Place , Euston"
  },
  {
    "start_station_name": "Portland Place, Marylebone"
  },
  {
    "start_station_name": "Crabtree Lane, Fulham"
  },
  {
    "start_station_name": "Ladbroke Grove Central, Ladbroke Grove"
  },
  {
    "start_station_name": "Riverlight North, Nine Elms"
  },
  {
    "start_station_name": "Fishermans Walk West, Canary Wharf"
  },
  {
    "start_station_name": "Pont Street, Knightsbridge"
  },
  {
    "start_station_name": "Crawford Street, Marylebone"
  },
  {
    "start_station_name": "Bell Street , Marylebone"
  },
  {
    "start_station_name": "Ormonde Gate, Chelsea"
  },
  {
    "start_station_name": "Here East North, Queen Elizabeth Olympic Park"
  },
  {
    "start_station_name": "Eastbourne Mews, Paddington"
  },
  {
    "start_station_name": "Doric Way , Somers Town"
  },
  {
    "start_station_name": "Thorndike Close, West Chelsea"
  },
  {
    "start_station_name": "Union Grove, Wandsworth Road"
  },
  {
    "start_station_name": "Pitfield Street Central, Hoxton"
  },
  {
    "start_station_name": "Upper Grosvenor Street, Mayfair"
  },
  {
    "start_station_name": "Penfold Street, Marylebone"
  },
  {
    "start_station_name": "One Tower Bridge, Bermondsey"
  },
  {
    "start_station_name": "Southampton Place, Holborn"
  },
  {
    "start_station_name": "Hoxton Station, Hoxton"
  },
  {
    "start_station_name": "Copper Box Arena, Queen Elizabeth Olympic Park"
  },
  {
    "start_station_name": "Courland Grove, Wandsworth Road"
  },
  {
    "start_station_name": "Chelsea Bridge, Pimlico"
  },
  {
    "start_station_name": "Paddington Green, Paddington"
  },
  {
    "start_station_name": "Clarence Walk, Stockwell"
  },
  {
    "start_station_name": "Spencer Park, Wandsworth Common"
  },
  {
    "start_station_name": "Hammersmith Road, Hammersmith"
  },
  {
    "start_station_name": "Kensington Gore, Knightsbridge"
  },
  {
    "start_station_name": "Montserrat Road , Putney"
  },
  {
    "start_station_name": "Snow Hill, Farringdon"
  },
  {
    "start_station_name": "Regency Street, Westminster"
  },
  {
    "start_station_name": "Chadwell Street, Angel"
  },
  {
    "start_station_name": "Alpha Grove, Millwall"
  },
  {
    "start_station_name": "Doddington Grove, Kennington"
  },
  {
    "start_station_name": "Queen Street, Bank"
  },
  {
    "start_station_name": "Lansdowne Road, Ladbroke Grove"
  },
  {
    "start_station_name": "West Cromwell Road, Earl's Court"
  },
  {
    "start_station_name": "Tysoe Street, Clerkenwell"
  },
  {
    "start_station_name": "Westferry DLR, Limehouse"
  },
  {
    "start_station_name": "Harriet Street, Knightsbridge"
  },
  {
    "start_station_name": "Goswell Road (City Uni), Finsbury"
  },
  {
    "start_station_name": "London Zoo Car Park, Regent's Park"
  },
  {
    "start_station_name": "North Wharf Road, Paddington"
  },
  {
    "start_station_name": "Campden Hill Road, Notting Hill"
  },
  {
    "start_station_name": "Bermondsey Street, Bermondsey"
  },
  {
    "start_station_name": "Bishop's Avenue, Fulham"
  },
  {
    "start_station_name": "Aston Street, Stepney"
  },
  {
    "start_station_name": "Waterloo Station 3, Waterloo"
  },
  {
    "start_station_name": "Heath Road, Battersea"
  },
  {
    "start_station_name": "Merchant Street, Bow"
  },
  {
    "start_station_name": "Mile End Park Leisure Centre, Mile End"
  },
  {
    "start_station_name": "Gloucester Street, Pimlico"
  },
  {
    "start_station_name": "Hardwick Street, Clerkenwell"
  },
  {
    "start_station_name": "Hatton Wall, Holborn"
  },
  {
    "start_station_name": "Bath Street, St. Luke's"
  },
  {
    "start_station_name": "Grant Road West, Clapham Junction"
  },
  {
    "start_station_name": "Sancroft Street, Vauxhall"
  },
  {
    "start_station_name": "Normand Park, West Kensington"
  },
  {
    "start_station_name": "Boston Place, Marylebone"
  },
  {
    "start_station_name": "Windsor Terrace, Hoxton"
  },
  {
    "start_station_name": "Wells Street, Fitzrovia"
  },
  {
    "start_station_name": "Drummond Street , Euston"
  },
  {
    "start_station_name": "Hawley Crescent, Camden Town"
  },
  {
    "start_station_name": "Royal College Street, Camden Town"
  },
  {
    "start_station_name": "Great Dover Street, The Borough"
  },
  {
    "start_station_name": "Prince of Wales Drive, Battersea Park"
  },
  {
    "start_station_name": "Bunhill Row, Moorgate"
  },
  {
    "start_station_name": "Fawcett Close, Clapham Junction"
  },
  {
    "start_station_name": "West Kensington Station, West Kensington"
  },
  {
    "start_station_name": "Grosvenor Road, Pimlico"
  },
  {
    "start_station_name": "Palissy Street, Shoreditch"
  },
  {
    "start_station_name": "Old Brompton Road, South Kensington"
  },
  {
    "start_station_name": "Belvedere Road 1, South Bank"
  },
  {
    "start_station_name": "Bank of England Museum, Bank"
  },
  {
    "start_station_name": "St Martins Close, Camden Town"
  },
  {
    "start_station_name": "Naval Row, Blackwall"
  },
  {
    "start_station_name": "Jubilee Street, Stepney"
  },
  {
    "start_station_name": "Drayton Gardens, West Chelsea"
  },
  {
    "start_station_name": "Parson's Green , Parson's Green"
  },
  {
    "start_station_name": "Park Road (Baker Street), Regent's Park"
  },
  {
    "start_station_name": "Golden Lane, Barbican"
  },
  {
    "start_station_name": "Central House, Aldgate"
  },
  {
    "start_station_name": "Clarges Street, Mayfair"
  },
  {
    "start_station_name": "William Morris Way, Sands End"
  },
  {
    "start_station_name": "Ilchester Place, Kensington"
  },
  {
    "start_station_name": "Globe Town Market, Bethnal Green"
  },
  {
    "start_station_name": "Natural History Museum, South Kensington"
  },
  {
    "start_station_name": "Bishop's Bridge Road East, Bayswater"
  },
  {
    "start_station_name": "Broadley Terrace, Marylebone"
  },
  {
    "start_station_name": "Stepney Green Station, Stepney"
  },
  {
    "start_station_name": "Bromley High Street, Bromley"
  },
  {
    "start_station_name": "New Spring Gardens Walk, Vauxhall"
  },
  {
    "start_station_name": "Kensington Church Street, Kensington"
  },
  {
    "start_station_name": "LMU Commercial Road, Whitechapel"
  },
  {
    "start_station_name": "Palace Gardens Terrace, Notting Hill"
  },
  {
    "start_station_name": "Blackfriars Road, Southwark"
  },
  {
    "start_station_name": "Malet Street, Bloomsbury"
  },
  {
    "start_station_name": "Stratford Station, Stratford"
  },
  {
    "start_station_name": "Gaywood  Street, Elephant & Castle"
  },
  {
    "start_station_name": "Erin Close, Walham Green"
  },
  {
    "start_station_name": "Nantes Close, Clapham Junction"
  },
  {
    "start_station_name": "Great Titchfield Street, Fitzrovia"
  },
  {
    "start_station_name": "Limburg Road, Clapham Junction"
  },
  {
    "start_station_name": "Dickens Square, Borough"
  },
  {
    "start_station_name": "Bevington Road West, North Kensington"
  },
  {
    "start_station_name": "Lincoln's Inn Fields, Holborn"
  },
  {
    "start_station_name": "Broadcasting House, Marylebone"
  },
  {
    "start_station_name": "Smith Square, Westminster"
  },
  {
    "start_station_name": "Peterborough Road, Sands End"
  },
  {
    "start_station_name": "Claremont Square, Angel"
  },
  {
    "start_station_name": "Hoxton Station, Haggerston"
  },
  {
    "start_station_name": "Stewart's Road, Wandsworth Road"
  },
  {
    "start_station_name": "St. Martin's Street, West End"
  },
  {
    "start_station_name": "Battersea Church Road, Battersea"
  },
  {
    "start_station_name": "Putney Bridge Road, East Putney"
  },
  {
    "start_station_name": "Buxton Street 1, Shoreditch"
  },
  {
    "start_station_name": "Macclesfield Rd, St Lukes"
  },
  {
    "start_station_name": "Kennington Lane Tesco, Vauxhall"
  },
  {
    "start_station_name": "Gwendwr Road, West Kensington"
  },
  {
    "start_station_name": "Harrington Square 1, Camden Town"
  },
  {
    "start_station_name": "New Road 1 , Whitechapel"
  },
  {
    "start_station_name": "Portugal Street, Holborn"
  },
  {
    "start_station_name": "Antill Road, Mile End"
  },
  {
    "start_station_name": "Baylis Road, Waterloo"
  },
  {
    "start_station_name": "Grenfell Road, Avondale"
  },
  {
    "start_station_name": "Southwark Station 1, Southwark"
  },
  {
    "start_station_name": "Colombo Street, Southwark"
  },
  {
    "start_station_name": "Curzon Street, Mayfair"
  },
  {
    "start_station_name": "Sandilands Road, Walham Green"
  },
  {
    "start_station_name": "New North Road 2, Hoxton"
  },
  {
    "start_station_name": "Vicarage Gate, Kensington"
  },
  {
    "start_station_name": "Lansdowne Walk, Ladbroke Grove"
  },
  {
    "start_station_name": "Walmer Road, Avondale"
  },
  {
    "start_station_name": "Aylward Street, Stepney"
  },
  {
    "start_station_name": "Rossmore Road, Marylebone"
  },
  {
    "start_station_name": "Long Lane , Bermondsey"
  },
  {
    "start_station_name": "Clifton Street, Shoreditch"
  },
  {
    "start_station_name": "Chrisp Street Market, Poplar"
  },
  {
    "start_station_name": "Vaughan Way, Wapping"
  },
  {
    "start_station_name": "St. Bride Street, Holborn"
  },
  {
    "start_station_name": "Lindfield Street, Poplar"
  },
  {
    "start_station_name": "St. John Street, Finsbury"
  },
  {
    "start_station_name": "Scala Street, Fitzrovia"
  },
  {
    "start_station_name": "Christian Street, Whitechapel"
  },
  {
    "start_station_name": "Chancery Lane, Holborn"
  },
  {
    "start_station_name": "Coomer Place, West Kensington"
  },
  {
    "start_station_name": "Goldsmiths Row, Haggerston"
  },
  {
    "start_station_name": "Evesham Street, Avondale"
  },
  {
    "start_station_name": "Queen's Gate (South), South Kensington"
  },
  {
    "start_station_name": "Chapel Place, Marylebone"
  },
  {
    "start_station_name": "BBC White City, White City"
  },
  {
    "start_station_name": "George Place Mews, Marylebone"
  },
  {
    "start_station_name": "Museum of London, Barbican"
  },
  {
    "start_station_name": "Imperial Wharf Station"
  },
  {
    "start_station_name": "Hurlingham Park, Parsons Green"
  },
  {
    "start_station_name": "South Audley Street, Mayfair"
  },
  {
    "start_station_name": "Eversholt Street , Camden Town"
  },
  {
    "start_station_name": "Putney Rail Station, Putney"
  },
  {
    "start_station_name": "Sail Street, Vauxhall"
  },
  {
    "start_station_name": "Freston Road, Avondale"
  },
  {
    "start_station_name": "Holden Street, Battersea"
  },
  {
    "start_station_name": "Finsbury Library , Finsbury"
  },
  {
    "start_station_name": "Stainsby Road , Poplar"
  },
  {
    "start_station_name": "South Park, Sands End"
  },
  {
    "start_station_name": "Devonshire Square, Liverpool Street"
  },
  {
    "start_station_name": "Vincent Square, Westminster"
  },
  {
    "start_station_name": "Margery Street, Clerkenwell"
  },
  {
    "start_station_name": "Killick Street, King's Cross"
  },
  {
    "start_station_name": "Vauxhall Walk, Vauxhall"
  },
  {
    "start_station_name": "Charlotte Terrace, Angel"
  },
  {
    "start_station_name": "Guildhouse Street, Victoria"
  },
  {
    "start_station_name": "The Vale, Chelsea"
  },
  {
    "start_station_name": "Dorothy Road, Clapham Junction"
  },
  {
    "start_station_name": "Theobald's Road , Holborn"
  },
  {
    "start_station_name": "Hermitage Court, Wapping"
  },
  {
    "start_station_name": "Pennington Street, Wapping"
  },
  {
    "start_station_name": "Warwick Road, Olympia"
  },
  {
    "start_station_name": "Thurtle Road, Haggerston"
  },
  {
    "start_station_name": "Kensington Olympia Station, Olympia"
  },
  {
    "start_station_name": "Barbican Centre, Barbican"
  },
  {
    "start_station_name": "Alfred Place, Bloomsbury"
  },
  {
    "start_station_name": "Webber Street , Southwark"
  },
  {
    "start_station_name": "Preston's Road, Cubitt Town"
  },
  {
    "start_station_name": "Imperial Road, Sands End"
  },
  {
    "start_station_name": "Albert Square, Stockwell"
  },
  {
    "start_station_name": "Royal Avenue 2, Chelsea"
  },
  {
    "start_station_name": "Upcerne Road, West Chelsea"
  },
  {
    "start_station_name": "Malmesbury Road, Bow"
  },
  {
    "start_station_name": "Ram Street, Wandsworth"
  },
  {
    "start_station_name": "Furze Green, Bow"
  },
  {
    "start_station_name": "Russell Gardens, Olympia"
  },
  {
    "start_station_name": "Clarkson Street, Bethnal Green"
  },
  {
    "start_station_name": "Canton Street, Poplar"
  },
  {
    "start_station_name": "Taviton Street, Bloomsbury"
  },
  {
    "start_station_name": "St. John's Wood Road, St. John's Wood"
  },
  {
    "start_station_name": "Orbel Street, Battersea"
  },
  {
    "start_station_name": "Lisson Grove, St. John's Wood"
  },
  {
    "start_station_name": "Grant Road Central, Clapham Junction"
  },
  {
    "start_station_name": "Walworth Road, Southwark"
  },
  {
    "start_station_name": "Garnet Street, Shadwell"
  },
  {
    "start_station_name": "Riverlight South, Nine Elms"
  },
  {
    "start_station_name": "Mallory Street, Marylebone"
  },
  {
    "start_station_name": "Falkirk Street, Hoxton"
  },
  {
    "start_station_name": "The Tennis Courts, Regent's Park"
  },
  {
    "start_station_name": "Sirdar Road, Avondale"
  },
  {
    "start_station_name": "Kennington Station, Kennington"
  },
  {
    "start_station_name": "Killick Street, Kings Cross"
  },
  {
    "start_station_name": "Everington Street, Fulham"
  },
  {
    "start_station_name": "Butler Place, Westminster"
  },
  {
    "start_station_name": "Spanish Road, Clapham Junction"
  },
  {
    "start_station_name": "Geraldine Street, Elephant & Castle"
  },
  {
    "start_station_name": "Murray Grove , Hoxton"
  },
  {
    "start_station_name": "Altab Ali Park, Whitechapel"
  },
  {
    "start_station_name": "Grant Road East, Clapham Junction"
  },
  {
    "start_station_name": "Ampton Street , Clerkenwell"
  },
  {
    "start_station_name": "Victory place, Walworth"
  },
  {
    "start_station_name": "Colet Gardens, Hammersmith"
  },
  {
    "start_station_name": "Castalia Square, Cubitt Town"
  },
  {
    "start_station_name": "Bevington Road, North Kensington"
  },
  {
    "start_station_name": "South Quay East, Canary Wharf"
  },
  {
    "start_station_name": "Durant Street, Bethnal Green"
  },
  {
    "start_station_name": "Marloes Road, Kensington"
  },
  {
    "start_station_name": "Queensdale Road, Shepherd's Bush"
  },
  {
    "start_station_name": "Limburg Road, Clapham Common"
  },
  {
    "start_station_name": "Here East South, Queen Elizabeth Olympic Park"
  },
  {
    "start_station_name": "Hansard Mews, Shepherds Bush"
  },
  {
    "start_station_name": "Spanish Road, Wandsworth"
  },
  {
    "start_station_name": "Devons Road, Bow"
  },
  {
    "start_station_name": "Sugden Road, Battersea"
  },
  {
    "start_station_name": "Percival Street, Finsbury"
  },
  {
    "start_station_name": "Denyer Street, Knightsbridge"
  },
  {
    "start_station_name": "Greenberry Street, St.John's Wood"
  },
  {
    "start_station_name": "Southerton Road, Hammersmith"
  },
  {
    "start_station_name": "Lambeth Palace Road, Waterloo"
  },
  {
    "start_station_name": "Culvert Road, Battersea"
  },
  {
    "start_station_name": "Selby Street, Whitechapel"
  },
  {
    "start_station_name": "Cleveland Gardens, Bayswater"
  },
  {
    "start_station_name": "Clifford Street, Mayfair"
  },
  {
    "start_station_name": "Lansdowne Walk, Notting Hill"
  },
  {
    "start_station_name": "Lodge Road, St. John's Wood"
  },
  {
    "start_station_name": "Esmond Street, Putney"
  },
  {
    "start_station_name": "Rectory Square, Stepney"
  },
  {
    "start_station_name": "Hibbert Street, Clapham Junction"
  },
  {
    "start_station_name": "Clapham Common Northside, Clapham Common"
  },
  {
    "start_station_name": "St Katharines Way, Tower"
  },
  {
    "start_station_name": "Drayton Gardens, Chelsea"
  },
  {
    "start_station_name": "Normand Park, Fulham"
  },
  {
    "start_station_name": "Birkenhead Street, King's Cross"
  },
  {
    "start_station_name": "Breams Buildings, Holborn"
  },
  {
    "start_station_name": "Upper Richmond Road, East Putney"
  },
  {
    "start_station_name": "St. John's Park, Cubitt Town"
  },
  {
    "start_station_name": "Halford Road, West Kensington"
  },
  {
    "start_station_name": "Oval Way, Vauxhall"
  },
  {
    "start_station_name": "Lambeth Road, Vauxhall"
  },
  {
    "start_station_name": "Abingdon Green, Great College Street"
  },
  {
    "start_station_name": "Baldwin Street, St. Luke's"
  },
  {
    "start_station_name": "Lollard Street, Vauxhall"
  },
  {
    "start_station_name": "Walmer Road, Notting Hill"
  },
  {
    "start_station_name": "Westfield Eastern Access Road, Shepherd's Bush"
  },
  {
    "start_station_name": "Stewart's Road, Nine Elms"
  },
  {
    "start_station_name": "Sheepcote Lane, Battersea"
  },
  {
    "start_station_name": "Bradmead, Nine Elms"
  },
  {
    "start_station_name": "Nantes Close, Wandsworth"
  },
  {
    "start_station_name": "Orsett Terrace, Bayswater"
  },
  {
    "start_station_name": "Greycoat Street , Westminster"
  },
  {
    "start_station_name": "Thessaly Road North, Wandsworth Road"
  },
  {
    "start_station_name": "Stockwell Roundabout, Stockwell"
  },
  {
    "start_station_name": "Queen Marys, Mile End"
  },
  {
    "start_station_name": "Columbia Road, Weavers"
  },
  {
    "start_station_name": "Millbank House, Pimlico"
  },
  {
    "start_station_name": "King Edward Walk, Waterloo"
  },
  {
    "start_station_name": "Bethnal Green Gardens, Bethnal Green"
  },
  {
    "start_station_name": "Victoria and Albert Museum, Cromwell Road"
  },
  {
    "start_station_name": "Gun Makers Lane, Old Ford"
  },
  {
    "start_station_name": "Cantrell Road, Bow"
  },
  {
    "start_station_name": "London Zoo, Regents Park"
  },
  {
    "start_station_name": "Cleveland Way, Bethnal Green"
  },
  {
    "start_station_name": "Kingsway, Covent Garden"
  },
  {
    "start_station_name": "Contact Centre, Southbury House"
  },
  {
    "start_station_name": "Limerston Street, Chelsea"
  },
  {
    "start_station_name": "Kensington Town Hall, Kensington"
  },
  {
    "start_station_name": "Russell Gardens, Holland Park"
  },
  {
    "start_station_name": "Albany Street, Regent's Park"
  },
  {
    "start_station_name": "Prince Albert Road, Regent's Park"
  },
  {
    "start_station_name": "Ingrave Street, Battersea"
  },
  {
    "start_station_name": "Battersea Power Station, Battersea Park"
  },
  {
    "start_station_name": "Harrington Square, Camden Town"
  },
  {
    "start_station_name": "Sidney Street, Stepney"
  },
  {
    "start_station_name": "Fawcett Close, Battersea"
  },
  {
    "start_station_name": "Austin Road, Battersea"
  },
  {
    "start_station_name": "Cadogan Gardens, Sloane Square"
  },
  {
    "start_station_name": "Ladbroke Grove Central, Notting Hill"
  },
  {
    "start_station_name": "Central House, Whitechapel"
  },
  {
    "start_station_name": "Thessaly Road North, Nine Elms"
  },
  {
    "start_station_name": "Clarges Street, West End"
  },
  {
    "start_station_name": "St. Mary and St. Michael Church, Stepney"
  },
  {
    "start_station_name": "Waterloo Roundabout, Waterloo"
  },
  {
    "start_station_name": "South Quay West, Canary Wharf"
  },
  {
    "start_station_name": "Harper Road, Borough"
  },
  {
    "start_station_name": "Lansdowne Way Bus Garage, Stockwell"
  },
  {
    "start_station_name": "Churchill Place, Canary Wharf"
  },
  {
    "start_station_name": "New Road  2, Whitechapel"
  },
  {
    "start_station_name": "Great Dover Street, Borough"
  },
  {
    "start_station_name": "St John's Park, Cubitt Town"
  },
  {
    "start_station_name": "Strata, Southwark"
  },
  {
    "start_station_name": "Halford Road, Fulham"
  },
  {
    "start_station_name": "Victory Place, Walworth"
  },
  {
    "start_station_name": "Blackfriars road, Southwark"
  },
  {
    "start_station_name": "St Martin's Close, Camden Town"
  },
  {
    "start_station_name": "Theobalds Road , Holborn"
  },
  {
    "start_station_name": "Coborn Street, Mile End"
  },
  {
    "start_station_name": "Oval Way, Lambeth"
  },
  {
    "start_station_name": "Pop Up Dock 1"
  },
  {
    "start_station_name": "Mechanical Workshop Penton"
  },
  {
    "start_station_name": "Monier Road, Newham"
  },
  {
    "start_station_name": "Pop Up Dock 2"
  },
  {
    "start_station_name": "Monier Road"
  },
  {
    "start_station_name": "LSP2"
  },
  {
    "start_station_name": "PENTON STREET COMMS TEST TERMINAL _ CONTACT MATT McNULTY"
  },
  {
    "start_station_name": "LSP1"
  }
]